llama_tools_aisee/__init__.py
llama_tools_aisee/__main__.py
llama_tools_aisee/convert_and_quantize.py
llama_tools_aisee/push_gguf.py
llama_tools_aisee/server.py
llama_tools_aisee/setup.py
llama_tools_aisee/setup_llama_cpp.py
llama_tools_aisee/utils.py
llama_tools_aisee/venv.py
llama_tools_aisee-0.1.6.dist-info/METADATA
llama_tools_aisee-0.1.6.dist-info/WHEEL
llama_tools_aisee-0.1.6.dist-info/entry_points.txt
llama_tools_aisee-0.1.6.dist-info/top_level.txt
llama_tools_aisee-0.1.6.dist-info/RECORD
