Metadata-Version: 2.4
Name: llama-tools-aisee
Version: 0.1.6
Summary: Utility for building and running llama.cpp
Author-email: Jaliya Nimantha <jaliya@ahlab.org>
Requires-Dist: huggingface_hub
